file_database/__init__.py
file_database/__version__.py
file_database/cli.py
file_database/disk_info.py
file_database/hasher.py
file_database/manager.py
file_database/parser.py
file_database/querier.py
file_database/querier_old.py
file_database-0.2.0.dist-info/METADATA
file_database-0.2.0.dist-info/WHEEL
file_database-0.2.0.dist-info/entry_points.txt
file_database-0.2.0.dist-info/top_level.txt
file_database-0.2.0.dist-info/RECORD
