Metadata-Version: 2.4
Name: file-database
Version: 0.2.0
Summary: Fast index and query of local files.
Author-email: Stephen J Mildenhall <mynl@me.com>
License: MIT
Classifier: Development Status :: 4 - Beta
Classifier: License :: OSI Approved :: MIT License
Classifier: Programming Language :: Python :: 3.10
Classifier: Topic :: Utilities
Requires-Python: >=3.10
Requires-Dist: pandas
Requires-Dist: pyarrow
Requires-Dist: click
Requires-Dist: pyyaml
Requires-Dist: wmi
